eth_address_dump/__init__.py
eth_address_dump/eth_address_dump.py
eth_address_dump-0.1.9.dist-info/LICENSE
eth_address_dump-0.1.9.dist-info/METADATA
eth_address_dump-0.1.9.dist-info/WHEEL
eth_address_dump-0.1.9.dist-info/entry_points.txt
eth_address_dump-0.1.9.dist-info/top_level.txt
eth_address_dump-0.1.9.dist-info/RECORD
