Metadata-Version: 2.1
Name: eth-address-dump
Version: 0.1.9
Summary: A utility for dump eth address from mnemonic words or private key or public key
Home-page: https://github.com/10gic/eth-address-dump
Author: cig01
License: MIT License
Platform: any
Classifier: Development Status :: 4 - Beta
Classifier: Environment :: Console
Classifier: Intended Audience :: Developers
Classifier: License :: OSI Approved :: GNU Affero General Public License v3 or later (AGPLv3+)
Classifier: Operating System :: OS Independent
Classifier: Programming Language :: Python
Classifier: Programming Language :: Python :: 3.7
Classifier: Programming Language :: Python :: 3.8
Classifier: Topic :: Software Development :: Libraries :: Python Modules
Classifier: Topic :: Text Processing
Classifier: Topic :: Utilities
Requires-Python: >=3
Requires-Dist: pysha3
Requires-Dist: ecdsa
Requires-Dist: base58
